airflownetwork/__about__.py
airflownetwork/__init__.py
airflownetwork/__main__.py
airflownetwork/auditor.py
airflownetwork/cli/__init__.py
airflownetwork-1.0.1.dist-info/METADATA
airflownetwork-1.0.1.dist-info/WHEEL
airflownetwork-1.0.1.dist-info/entry_points.txt
airflownetwork-1.0.1.dist-info/licenses/LICENSE.txt
airflownetwork-1.0.1.dist-info/RECORD
