Metadata-Version: 2.1
Name: airflownetwork
Version: 1.0.1
Summary: Examine EnergyPlus AirflowNetwork models
Project-URL: Documentation, https://github.com/building-physics/airflownetwork-python#readme
Project-URL: Issues, https://github.com/building-physics/airflownetwork-python/issues
Project-URL: Source, https://github.com/building-physics/airflownetwork-python
Author-email: "Jason W. DeGraw" <jason.degraw@gmail.com>
License-Expression: BSD-3-Clause
License-File: LICENSE.txt
Classifier: Development Status :: 4 - Beta
Classifier: Programming Language :: Python
Classifier: Programming Language :: Python :: 3.7
Classifier: Programming Language :: Python :: 3.8
Classifier: Programming Language :: Python :: 3.9
Classifier: Programming Language :: Python :: 3.10
Classifier: Programming Language :: Python :: 3.11
Classifier: Programming Language :: Python :: Implementation :: CPython
Classifier: Programming Language :: Python :: Implementation :: PyPy
Requires-Python: >=3.7
Requires-Dist: click
